handyllm/__init__.py
handyllm/__main__.py
handyllm/_constants.py
handyllm/_io.py
handyllm/_str_enum.py
handyllm/_utils.py
handyllm/cache_manager.py
handyllm/cli.py
handyllm/endpoint_manager.py
handyllm/hprompt.py
handyllm/openai_api.py
handyllm/openai_client.py
handyllm/prompt_converter.py
handyllm/py.typed
handyllm/requestor.py
handyllm/run_config.py
handyllm/types.py
handyllm/utils.py
handyllm-0.10.0.dist-info/licenses/LICENSE
handyllm-0.10.0.dist-info/METADATA
handyllm-0.10.0.dist-info/WHEEL
handyllm-0.10.0.dist-info/entry_points.txt
handyllm-0.10.0.dist-info/top_level.txt
handyllm-0.10.0.dist-info/RECORD
