Metadata-Version: 2.4
Name: HandyLLM
Version: 0.10.0
Summary: A handy toolkit for using LLM.
Author-email: Atomie CHEN <atomic_cwh@163.com>
Project-URL: Homepage, https://github.com/atomiechen/HandyLLM
Project-URL: Bug Tracker, https://github.com/atomiechen/HandyLLM/issues
Project-URL: Changelog, https://github.com/atomiechen/HandyLLM/blob/master/CHANGELOG.md
Keywords: LLM,Large Language Model,Prompt,OpenAI,API
Classifier: Programming Language :: Python :: 3
Classifier: License :: OSI Approved :: MIT License
Classifier: Operating System :: OS Independent
Requires-Python: >=3.8
License-File: LICENSE
Requires-Dist: httpx>=0.28.1
Requires-Dist: mergedeep>=1.3.4
Requires-Dist: python-dotenv>=1.0.1
Requires-Dist: python-frontmatter>=1.1.0
Requires-Dist: pyyaml>=6.0.2
Requires-Dist: requests>=2.32.4
Requires-Dist: typing-extensions>=4.13.2
Dynamic: license-file
